pixtreme/__init__.py
pixtreme-0.8.6.dist-info/METADATA
pixtreme-0.8.6.dist-info/WHEEL
pixtreme-0.8.6.dist-info/licenses/LICENSE
pixtreme-0.8.6.dist-info/RECORD
