Metadata-Version: 2.4
Name: pixtreme
Version: 0.8.6
Summary: pixtreme: A High-Performance Graphics Library with CUDA Support
Project-URL: repository, https://github.com/sync-dev-org/pixtreme
Project-URL: issues, https://github.com/sync-dev-org/pixtreme/issues
Author-email: minamik <mia@sync.dev>
License-Expression: MIT
License-File: LICENSE
Classifier: Development Status :: 4 - Beta
Classifier: Environment :: GPU :: NVIDIA CUDA :: 12
Classifier: Intended Audience :: Developers
Classifier: License :: OSI Approved :: MIT License
Classifier: Operating System :: Microsoft :: Windows
Classifier: Operating System :: POSIX :: Linux
Classifier: Programming Language :: Python :: 3.12
Classifier: Programming Language :: Python :: 3.13
Classifier: Topic :: Multimedia :: Graphics
Classifier: Topic :: Software Development :: Libraries
Requires-Python: >=3.12
Requires-Dist: pixtreme-core>=0.8.6
Provides-Extra: aces
Requires-Dist: pixtreme-aces>=0.8.6; extra == 'aces'
Provides-Extra: all
Requires-Dist: pixtreme-aces>=0.8.6; extra == 'all'
Requires-Dist: pixtreme-draw>=0.8.6; extra == 'all'
Requires-Dist: pixtreme-filter>=0.8.6; extra == 'all'
Requires-Dist: pixtreme-upscale[tensorrt]>=0.8.6; extra == 'all'
Provides-Extra: draw
Requires-Dist: pixtreme-draw>=0.8.6; extra == 'draw'
Provides-Extra: filter
Requires-Dist: pixtreme-filter>=0.8.6; extra == 'filter'
Provides-Extra: full
Requires-Dist: pixtreme-aces>=0.8.6; extra == 'full'
Requires-Dist: pixtreme-draw>=0.8.6; extra == 'full'
Requires-Dist: pixtreme-filter>=0.8.6; extra == 'full'
Requires-Dist: pixtreme-legacy>=0.8.6; extra == 'full'
Requires-Dist: pixtreme-upscale[tensorrt]>=0.8.6; extra == 'full'
Provides-Extra: legacy
Requires-Dist: pixtreme-legacy>=0.8.6; extra == 'legacy'
Provides-Extra: upscale
Requires-Dist: pixtreme-upscale>=0.8.6; extra == 'upscale'
